{
"name":"Kyle Hyubert",
"version":1.8,
"str":{"value":"11","shortname":"str","name":"Strength","roll":"11-","damage":"","value2":"11","roll2":"11","damage2":""},
"dex":{"value":"13","shortname":"dex","name":"Dexterity","roll":"12-","damage":"","value2":"13","roll2":"12","damage2":""},
"con":{"value":"15","shortname":"con","name":"Constitution","roll":"12-","damage":"","value2":"15","roll2":"12","damage2":""},
"int":{"value":"13","shortname":"int","name":"Intelligence","roll":"12-","damage":"","value2":"13","roll2":"12","damage2":""},
"ego":{"value":"15","shortname":"ego","name":"Ego","roll":"12-","damage":"","value2":"15","roll2":"12","damage2":""},
"pre":{"value":"13","shortname":"pre","name":"Presence","roll":"12-","damage":"","value2":"13","roll2":"12","damage2":""},
"spd":{"value":"4","shortname":"spd","name":"Speed","roll":"","damage":"","value2":"4","roll2":"","damage2":""},
"ocv":{"value":"5","shortname":"ocv","name":"Offensive Combat Value","roll":"","damage":"","value2":"5","roll2":"","damage2":""},
"dcv":{"value":"6","shortname":"dcv","name":"Defensive Combat Value","roll":"","damage":"","value2":"6","roll2":"","damage2":""},
"omcv":{"value":"6","shortname":"omcv","name":"Offensive Mental Combat Value","roll":"","damage":"","value2":"6","roll2":"","damage2":""},
"dmcv":{"value":"4","shortname":"dmcv","name":"Defensive Mental Combat Value","roll":"","damage":"","value2":"4","roll2":"","damage2":""},
"pd":{"value":"7","shortname":"pd","name":"Physical Defence","roll":"","damage":"","value2":"12","roll2":"","damage2":""},
"pdr":{"value":"0","shortname":"pdr","name":"Physical Resistant Defence","roll":"","damage":"","value2":"5","roll2":"","damage2":""},
"ed":{"value":"8","shortname":"ed","name":"Energy Defence","roll":"","damage":"","value2":"13","roll2":"","damage2":""},
"edr":{"value":"0","shortname":"edr","name":"Energy Resistant Defence","roll":"","damage":"","value2":"5","roll2":"","damage2":""},
"per":{"value":"12-","shortname":"per","name":"Perception Roll","roll":"12-","damage":""},
"rec":{"value":"12","shortname":"rec","name":"Recovery","roll":"","damage":"","value2":"12","roll2":"","damage2":""},
"body":{"value":"13","shortname":"body","name":"Body","roll":"","damage":"","value2":"13","roll2":"","damage2":""},
"end":{"value":"50","shortname":"end","name":"Endurance","roll":"","damage":"","value2":"50","roll2":"","damage2":""},
"stun":{"value":"44","shortname":"stun","name":"Stun","roll":"","damage":"","value2":"44","roll2":"","damage2":""},
"movement":{
"run":{"combat":"8m","noncombat":"16m","icon":"ui_run"},
"swim":{"combat":"54m","noncombat":"108m","icon":"ui_swim"},
"teleport":{"combat":"42m","noncombat":"84m","icon":"ui_teleport"},
"leap":{"combat":"4m","noncombat":"8m","icon":"ui_leap"}},
"skills":[
	{"name":"Perception","roll":"12-"},
	{"name":"Acting","roll":"8-"},
	{"name":"Climbing","roll":"8-"},
	{"name":"Concealment","roll":"8-"},
	{"name":"Deduction","roll":"8-"},
	{"name":"Paramedics","roll":"8-"},
	{"name":"Persuasion","roll":"8-"},
	{"name":"TF: Common Motorized Ground Vehicles, Custom Adder","roll":""},
	{"name":"Language: English (completely fluent; literate) (4 Active Points)","roll":""},
	{"name":"KS (Custom Adder)","roll":"11-"},
	{"name":"KS","roll":"8-"},
	{"name":"PS (Custom Adder)","roll":"11-"},
	{"name":"Breakfall","roll":"12-"},
	{"name":"Stealth","roll":"12-"},
	{"name":"Mechanics","roll":"12-"},
	{"name":"Navigation (Land, Marine)","roll":"12-"},
	{"name":"Conversation","roll":"12-"},
	{"name":"Charm","roll":"12-"},
	{"name":"Shadowing","roll":"12-"}],
"attacks":[
	{"name":"Lure of Sleep","type":"Mental Blast","damage":"4d6","range":"LOS","input":"Human","level":"4","end":"4","active":"40","base":"40","XMLID":"EGOATTACK","strMod":false},
	{"name":"Sirens' Song","type":"Mental Illusions","damage":"8d6","range":"LOS","input":"Human","level":"8","end":"4","active":"40","base":"40","XMLID":"MENTALILLUSIONS","strMod":false},
	{"name":"Call of the Sea","type":"Teleportation","damage":"16m","range":"","input":"","level":"16","end":"4","active":"40","base":"16","XMLID":"TELEPORTATION","strMod":false},
	{"name":"Lost to the Dream","type":"Drain","damage":"4d6 (standard effect: 12 points)","range":"400m","input":"EGO","level":"4","end":"4","active":"40","base":"40","XMLID":"DRAIN","strMod":"4d6 (standard effect: 12 points)"},
	{"name":"Waterball","type":"Blast","damage":"8d6","range":"400m","input":"ED","level":"8","end":"4","active":"40","base":"40","XMLID":"ENERGYBLAST","strMod":false},
	{"name":"Hydrokinesis","type":"Telekinesis","damage":"(25 STR)","range":"390m","input":"","level":"25","end":"4","active":"39","base":"39","XMLID":"TELEKINESIS","strMod":true}],
"martialArts":[
	{"name":"Other Attacks","gameEdition":6 ,"ocvMod":0,"dcvMod":0,"dice":3,"halfDice":false,"effect":"Normal Attack","time":"½","level":"0","killingAttack":false,"active":"1","targetNumber":0,"targetCheck":false,"stunMultiplierMod":0,"tool":"Other Attacks:½ Phase, +0 OCV, +0 DCV, Normal attack","toHit":true,"againstOCV":false,"toPost":false,"post":"","rngMod":0,"abort":false}],
"rolls":[
	{"name":"Lure of Sleep","gameEdition":6,"tool":"4d6, Mental Blast (vs. Human) LOS, 4 end.","diceMod":0,"dice":4,"halfDice":false,"killingAttack":false,"targetNumber":0,"targetCheck":false,"strMod":false,"stunMultiplierMod":0},
	{"name":"Sirens' Song","gameEdition":6,"tool":"8d6, Mental Illusions (vs. Human) LOS, 4 end.","diceMod":0,"dice":8,"halfDice":false,"killingAttack":false,"targetNumber":0,"targetCheck":false,"strMod":false,"stunMultiplierMod":0},
	{"name":"Call of the Sea","gameEdition":6,"tool":"16m, Teleportation , 4 end.","diceMod":16,"dice":16,"halfDice":false,"killingAttack":false,"targetNumber":0,"targetCheck":false,"strMod":false,"stunMultiplierMod":0},
	{"name":"Lost to the Dream","gameEdition":6,"tool":"4d6 (standard effect: 12 points), Drain (vs. EGO) 400m, 4 end.","diceMod":0,"dice":4,"halfDice":false,"killingAttack":false,"targetNumber":0,"targetCheck":false,"strMod":"4d6 (standard effect: 12 points)","stunMultiplierMod":0},
	{"name":"Waterball","gameEdition":6,"tool":"8d6, Blast (vs. ED) 400m, 4 end.","diceMod":0,"dice":8,"halfDice":false,"killingAttack":false,"targetNumber":0,"targetCheck":false,"strMod":false,"stunMultiplierMod":0},
	{"name":"Hydrokinesis","gameEdition":6,"tool":"(25 STR), Telekinesis 390m, 4 end.","diceMod":0,"dice":25,"halfDice":false,"killingAttack":false,"targetNumber":0,"targetCheck":false,"strMod":true,"stunMultiplierMod":0}],
"lightningReflex":[{"name":"Lightning Reflexes","levels":0,"tool":"No Lightning Reflexes","isActive":false}]
}
